django_eventcalendar-0.3.4.dist-info/DESCRIPTION.rst
django_eventcalendar-0.3.4.dist-info/METADATA
django_eventcalendar-0.3.4.dist-info/metadata.json
django_eventcalendar-0.3.4.dist-info/RECORD
django_eventcalendar-0.3.4.dist-info/top_level.txt
django_eventcalendar-0.3.4.dist-info/WHEEL
eventcalendar/__init__.py
eventcalendar/admin.py
eventcalendar/apps.py
eventcalendar/fields.py
eventcalendar/forms.py
eventcalendar/importical.py
eventcalendar/load_geodata.py
eventcalendar/models.py
eventcalendar/parseclickability.py
eventcalendar/search_indexes.py
eventcalendar/settings.py
eventcalendar/tests.py
eventcalendar/urls.py
eventcalendar/utils.py
eventcalendar/views.py
eventcalendar/yelp.py
eventcalendar/fixtures/eventtypes.json
eventcalendar/fixtures/install_hstore.sql
eventcalendar/fixtures/venues.json
eventcalendar/fixtures/venuetypes.json
eventcalendar/fixtures/Neighborhoods_Philadelphia/Neighborhoods_Philadelphia.dbf
eventcalendar/fixtures/Neighborhoods_Philadelphia/Neighborhoods_Philadelphia.prj
eventcalendar/fixtures/Neighborhoods_Philadelphia/Neighborhoods_Philadelphia.sbn
eventcalendar/fixtures/Neighborhoods_Philadelphia/Neighborhoods_Philadelphia.sbx
eventcalendar/fixtures/Neighborhoods_Philadelphia/Neighborhoods_Philadelphia.shp
eventcalendar/fixtures/Neighborhoods_Philadelphia/Neighborhoods_Philadelphia.shx
eventcalendar/fixtures/Neighborhoods_Philadelphia/Neighborhoods_Philadelphia.xml
eventcalendar/management/__init__.py
eventcalendar/management/commands/__init__.py
eventcalendar/management/commands/index_events.py
eventcalendar/management/commands/setup_eventcalendar.py
eventcalendar/migrations/0001_initial.py
eventcalendar/migrations/0002_add_venue_img_dims.py
eventcalendar/migrations/0003_add_descriptions.py
eventcalendar/migrations/0004_add_external_id.py
eventcalendar/migrations/__init__.py
eventcalendar/static/.DS_Store
eventcalendar/static/eventcalendar/.DS_Store
eventcalendar/static/eventcalendar/bootstrap-datepaginator.css
eventcalendar/static/eventcalendar/bootstrap-datepaginator.js
eventcalendar/static/eventcalendar/hstore-widget.js
eventcalendar/static/eventcalendar/inlines.js
eventcalendar/static/eventcalendar/ion.rangeSlider.css
eventcalendar/static/eventcalendar/ion.rangeSlider.js
