Metadata-Version: 2.0
Name: django-eventcalendar
Version: 0.3.4
Summary: eventcalendar
Home-page: http://github.com/coordt/django-eventcalendar
Author: Corey Oordt
Author-email: coreyoordt@gmail.com
License: UNKNOWN
Platform: UNKNOWN
Classifier: Framework :: Django
Requires-Dist: pytz (==2015.4)
Requires-Dist: python-dateutil (==2.4.2)
Requires-Dist: django-hstore (==1.3.8)
Requires-Dist: python-social-auth (==0.2.11)
Requires-Dist: python-openid (==2.2.5)
Requires-Dist: requests
Requires-Dist: django-extra-views (==0.7.1)
Requires-Dist: django-crispy-forms (==1.5.1)
Requires-Dist: django-autocomplete-light (==2.2.6)
Requires-Dist: usaddress (==0.5.3)
Requires-Dist: geopy (==1.11.0)
Requires-Dist: django-massmedia (==1.3b1)
Requires-Dist: django-debugtools (==1.3)
Requires-Dist: django-haystack (==2.4.0)
Requires-Dist: elasticsearch (==2.1.0)
Requires-Dist: elasticsearch-dsl (==0.0.9)
Requires-Dist: future (==0.14.3)
Requires-Dist: httplib2 (==0.9.1)
Requires-Dist: icalendar (==3.9.1)
Requires-Dist: Metafone (==0.5)
Requires-Dist: oauth2 (==1.9.0.post1)
Requires-Dist: oauthlib (==0.7.2)
Requires-Dist: psycopg2 (==2.6.1)
Requires-Dist: PyJWT (==1.3.0)
Requires-Dist: python-crfsuite (==0.8.3)
Requires-Dist: requests-oauthlib (==0.5.0)
Requires-Dist: six (==1.9.0)
Requires-Dist: urllib3 (==1.12)
